CHANGES.txt
MANIFEST.in
README.rst
requirements.txt
setup.py
pyradio_nepal.egg-info/PKG-INFO
pyradio_nepal.egg-info/SOURCES.txt
pyradio_nepal.egg-info/dependency_links.txt
pyradio_nepal.egg-info/requires.txt
pyradio_nepal.egg-info/top_level.txt
src/pyradio-nepal
src/pyradio_nepal/__init__.py
src/pyradio_nepal/__main__.py
src/pyradio_nepal/main.py
src/pyradio_nepal/utils.py
src/pyradio_nepal/data/.radio_stations_json
src/pyradio_nepal/libradio/__init__.py
src/pyradio_nepal/libradio/player.py
src/pyradio_nepal/libradio/utils.py