Metadata-Version: 1.1
Name: pyradio-nepal
Version: 0.1.4
Summary: Commandline tool to listen all radio stations of Nepal
Home-page: https://github.com/sandipbgt/pyradio-nepal
Author: Sandip Bhagat
Author-email: sandipbgt@gmail.com
License: UNKNOWN
Platform: UNKNOWN
Classifier: Environment :: Console
Classifier: Programming Language :: Python :: 3
